pytorch_pca/__init__.py
pytorch_pca/_version.py
pytorch_pca/pca.py
pytorch_pca/pca_result.py
pytorch_pca/utils.py
pytorch_pca/methods/__init__.py
pytorch_pca/methods/bpca.py
pytorch_pca/methods/nipals.py
pytorch_pca/methods/ppca.py
pytorch_pca/methods/rnipals.py
pytorch_pca/methods/rpca.py
pytorch_pca/methods/svd.py
pytorch_pca/methods/svd_impute.py
pytorch_pca/methods/nlpca/__init__.py
pytorch_pca/methods/nlpca/nlpca.py
pytorch_pca/methods/nlpca/nlpca_net.py
pytorch_pca/methods/nlpca/nlpca_utils.py
pytorch_pca-0.1.3.dist-info/licenses/LICENSE
pytorch_pca-0.1.3.dist-info/METADATA
pytorch_pca-0.1.3.dist-info/WHEEL
pytorch_pca-0.1.3.dist-info/top_level.txt
pytorch_pca-0.1.3.dist-info/RECORD
