Metadata-Version: 2.4
Name: pytorch-pca
Version: 0.1.3
Summary: Comprehensive PyTorch implementation of PCA.
Author-email: Ricardo Yanzon <ricayanzon@gmail.com>
License-Expression: MIT
Project-URL: GitHub, https://github.com/ricayanzon/pytorch_pca
Project-URL: Issues, https://github.com/ricayanzon/pytorch_pca/issues
Keywords: PCA,principal component analysis,pytorch,torch,svd pca,SVD,Singular Value Decomposition,NIPALS,Nonlinear Iterative Partial Least Squares,Non-linear Iterative Partial Least Squares,RNIPALS,robust NIPALS,bpca,Bayesian PCA,ppca,Probabilistic PCA,SVD Impute,Iterative PCA,Robust PCA,Nonlinear PCA,Non-linear PCA
Classifier: Programming Language :: Python :: 3
Requires-Python: >=3.11
License-File: LICENSE
Requires-Dist: torch==2.7.1
Dynamic: license-file
